unix_socket_server/__init__.py
unix_socket_server/context/__init__.py
unix_socket_server/context/_context.py
unix_socket_server/server/__init__.py
unix_socket_server/server/_types.py
unix_socket_server/server/server.py
unix_socket_server/server/handlers/__init__.py
unix_socket_server/server/handlers/http/__init__.py
unix_socket_server/server/handlers/http/_http.py
unix_socket_server/server/handlers/stream/__init__.py
unix_socket_server/server/handlers/stream/_stream.py
unix_socket_server/server/response/__init__.py
unix_socket_server/server/response/_exceptions.py
unix_socket_server-0.0.5.dist-info/LICENCE
unix_socket_server-0.0.5.dist-info/METADATA
unix_socket_server-0.0.5.dist-info/WHEEL
unix_socket_server-0.0.5.dist-info/top_level.txt
unix_socket_server-0.0.5.dist-info/RECORD
