Metadata-Version: 2.1
Name: unix-socket-server
Version: 0.0.5
Summary: A single-threaded server for serving in-memory files via Unix sockets.
Home-page: https://github.com/erfanshekari/unix-socket-server
Author: Erfan Shekari
Author-email: erfan.dp.co@gmail.com
Project-URL: Bug Tracker, https://github.com/erfanshekari/unix-socket-server
Classifier: Programming Language :: Python :: 3
Classifier: License :: OSI Approved :: MIT License
Classifier: Operating System :: OS Independent
Requires-Python: >=3.4
License-File: LICENCE
